{
  "users": [
    {
      "email": "a111@gmail.com",
      "password": "$2a$10$YoPUq5SayG2rWWlhehT3k.4psaDT3wjtsybarI/x3NJ5KY9wKnYLK",
      "nickname": "a111",
      "id": 6
    }
  ],
  "income-item": [
    {
      "userId": 6,
      "title": "薪資",
      "id": 1
    },
    {
      "userId": 6,
      "title": "投資",
      "id": 2
    },
    {
      "userId": 6,
      "title": "贊助",
      "id": 3
    }
  ],
  "expenditure-item": [
    {
      "userId": 6,
      "title": "早餐",
      "id": 1
    },
    {
      "userId": 6,
      "title": "午餐",
      "id": 2
    },
    {
      "userId": 6,
      "title": "晚餐",
      "id": 3
    },
    {
      "userId": 6,
      "title": "衣服",
      "id": 4
    }
  ],
  "account": [
    {
      "userId": 6,
      "title": "生活費用",
      "initialMoney": 0,
      "monthlyAllocation": 20000,
      "currentMoney": 18900,
      "id": 1
    },
    {
      "userId": 6,
      "title": "旅遊基金",
      "initialMoney": 0,
      "monthlyAllocation": 10000,
      "currentMoney": 10000,
      "id": 2
    },
    {
      "userId": 6,
      "title": "醫療基金",
      "initialMoney": 0,
      "monthlyAllocation": 0,
      "currentMoney": 6000,
      "id": 3
    }
  ],
  "monthly-allocation": [
    {
      "userId": 6,
      "fixedIncome": 30000,
      "date": "15",
      "isEnable": 1,
      "id": 1
    }
  ],
  "balance-sheet": [
    {
      "userId": 6,
      "category": "income",
      "year": 2022,
      "month": "08",
      "day": "15",
      "money": 20000,
      "item": "薪資",
      "account": "生活費用",
      "time": "00:00",
      "title": "自動匯入 00:00 生活費用 薪資 20000",
      "isAutomaticImport": 1,
      "id": 1
    },
    {
      "userId": 6,
      "category": "income",
      "year": 2022,
      "month": "08",
      "day": "15",
      "money": 10000,
      "item": "薪資",
      "account": "旅遊基金",
      "time": "00:00",
      "title": "自動匯入 00:00 旅遊基金 薪資 10000",
      "isAutomaticImport": 1,
      "id": 2
    },
    {
      "userId": 6,
      "category": "expenditure",
      "year": "2022",
      "month": "08",
      "day": "27",
      "money": 1000,
      "item": "午餐",
      "account": "生活費用",
      "time": "11:10",
      "title": "11:10 生活費用 午餐 1000",
      "id": 3
    },
    {
      "userId": 6,
      "category": "income",
      "year": "2022",
      "month": "08",
      "day": "27",
      "money": 6000,
      "item": "投資",
      "account": "醫療基金",
      "time": "11:14",
      "title": "11:14 醫療基金 投資 6000",
      "id": 4
    },
    {
      "userId": 6,
      "category": "expenditure",
      "year": "2022",
      "month": "08",
      "day": "27",
      "money": 100,
      "item": "早餐",
      "account": "生活費用",
      "time": "11:15",
      "title": "11:15 生活費用 早餐 100",
      "id": 5
    }
  ]
}